{
  "type": "Feature",
  "properties": {
    "gn:admin1_code":"14",
    "gn:asciiname":"Belle Plaine",
    "gn:country_code":"GY",
    "gn:dem":3,
    "gn:feature_class":"P",
    "gn:feature_code":"PPLL",
    "gn:name":"Belle Plaine",
    "gn:population":0,
    "gn:timezone":"America/Guyana",
    "iso:country":"GY",
    "name:ceb_x_preferred":[
        "Belle Plaine"
    ],
    "name:ces_x_preferred":[
        "Belle Plaine"
    ],
    "name:deu_x_preferred":[
        "Belle Plaine"
    ],
    "name:fra_x_preferred":[
        "Belle Plaine"
    ],
    "name:ido_x_preferred":[
        "Belle Plaine"
    ],
    "name:ita_x_preferred":[
        "Belle Plaine"
    ],
    "name:kor_x_preferred":[
        "\ubca8\ud50c\ub808\uc778"
    ],
    "name:nld_x_preferred":[
        "Belle Plaine"
    ],
    "name:pol_x_preferred":[
        "Belle Plaine"
    ],
    "name:por_x_preferred":[
        "Belle Plaine"
    ],
    "name:rus_x_preferred":[
        "\u0411\u0435\u043b\u043b-\u041f\u043b\u0435\u0439\u043d"
    ],
    "name:spa_x_preferred":[
        "Belle Plaine"
    ],
    "name:srp_x_preferred":[
        "\u0411\u0435\u043b \u041f\u043b\u0435\u0458\u043d"
    ],
    "name:ukr_x_preferred":[
        "\u0411\u0435\u043b \u041f\u043b\u0435\u0439\u043d"
    ],
    "name:vol_x_preferred":[
        "Belle Plaine"
    ],
    "wof:name":"Belle Plaine",
    "wof:placetype":"locality"
},
  "geometry": {"coordinates":[-58.46516999999999,6.95955],"type":"Point"}
}