{
  "type": "Feature",
  "properties": {
    "gn:admin1_code":"14",
    "gn:asciiname":"Belle Plaine",
    "gn:country_code":"GY",
    "gn:dem":3,
    "gn:feature_class":"P",
    "gn:feature_code":"PPLL",
    "gn:name":"Belle Plaine",
    "gn:population":0,
    "gn:timezone":"America/Guyana",
    "iso:country":"GY",
    "wof:name":"Belle Plaine",
    "wof:placetype":"locality"
},
  "geometry": {"coordinates":[-58.46516999999999,6.95955],"type":"Point"}
}