{
  "type": "Feature",
  "properties": {
    "gn:admin1_code":"11",
    "gn:asciiname":"Isseneru Village",
    "gn:country_code":"GY",
    "gn:dem":107,
    "gn:feature_class":"P",
    "gn:feature_code":"PPL",
    "gn:name":"Isseneru Village",
    "gn:population":0,
    "gn:timezone":"America/Guyana",
    "iso:country":"GY",
    "wof:name":"Isseneru Village",
    "wof:placetype":"locality"
},
  "geometry": {"coordinates":[-60.33333,6.46667],"type":"Point"}
}