{
  "type": "Feature",
  "properties": {
    "gn:admin1_code":"10",
    "gn:asciiname":"Arakaka",
    "gn:country_code":"GY",
    "gn:dem":33,
    "gn:feature_class":"P",
    "gn:feature_code":"PPL",
    "gn:name":"Arakaka",
    "gn:population":0,
    "gn:timezone":"America/Guyana",
    "iso:country":"GY",
    "wof:name":"Arakaka",
    "wof:placetype":"locality"
},
  "geometry": {"coordinates":[-60.01667,7.58333],"type":"Point"}
}