{
  "type": "Feature",
  "properties": {
    "iso:country":"GY",
    "qs:gn_country":"GY",
    "qs:gn_fcode":"PPLX",
    "qs:gn_pop":0,
    "qs:name":"Lacytown",
    "qs:name_adm0":"Guyana",
    "qs:name_adm1":"Demerara-Mahaica",
    "qs:photos":70,
    "qs:photos_1k":14,
    "qs:photos_9k":1,
    "qs:photos_9r":2,
    "qs:photos_all":70,
    "qs:photos_sr":2,
    "qs:placetype":"Suburb",
    "qs:pop_sr":"0",
    "qs:woe_adm0":23424836,
    "wof:name":"Lacytown",
    "wof:placetype":"neighbourhood"
},
  "geometry": {"coordinates":[-58.16411,6.81284],"type":"Point"}
}