{
  "type": "Feature",
  "properties": {
    "gn:admin1_code":"16",
    "gn:asciiname":"Akawini Amerindian Village",
    "gn:country_code":"GY",
    "gn:dem":20,
    "gn:feature_class":"P",
    "gn:feature_code":"PPL",
    "gn:name":"Akawini Amerindian Village",
    "gn:population":0,
    "gn:timezone":"America/Guyana",
    "iso:country":"GY",
    "name:eng_x_preferred":[
        "Akawini Amerindian Village"
    ],
    "name:und_x_variant":[
        "Akawini Mission"
    ],
    "wof:name":"Akawini Amerindian Village",
    "wof:placetype":"locality"
},
  "geometry": {"coordinates":[-58.73281,7.37204],"type":"Point"}
}