{
  "type": "Feature",
  "properties": {
    "gn:admin1_code":"12",
    "gn:asciiname":"Diamond Place",
    "gn:country_code":"GY",
    "gn:dem":1,
    "gn:feature_class":"P",
    "gn:feature_code":"PPLL",
    "gn:name":"Diamond Place",
    "gn:population":0,
    "gn:timezone":"America/Guyana",
    "iso:country":"GY",
    "name:und_x_variant":[
        "Big Diamond",
        "Diamond Place",
        "Great Diamond",
        "Diamond"
    ],
    "wof:name":"Diamond Place",
    "wof:placetype":"locality"
},
  "geometry": {"coordinates":[-58.17712,6.72274],"type":"Point"}
}