{
  "type": "Feature",
  "properties": {
    "gn:admin1_code":"17",
    "gn:asciiname":"Arnik Village",
    "gn:country_code":"GY",
    "gn:dem":456,
    "gn:feature_class":"P",
    "gn:feature_code":"PPL",
    "gn:name":"Arnik Village",
    "gn:population":0,
    "gn:timezone":"America/Guyana",
    "iso:country":"GY",
    "wof:name":"Arnik Village",
    "wof:placetype":"locality"
},
  "geometry": {"coordinates":[-59.53333000000001,5.01667],"type":"Point"}
}