{
  "type": "Feature",
  "properties": {
    "gn:admin1_code":"19",
    "gn:asciiname":"Wai-Wai",
    "gn:country_code":"GY",
    "gn:dem":280,
    "gn:feature_class":"P",
    "gn:feature_code":"PPL",
    "gn:name":"Wai-Wai",
    "gn:population":0,
    "gn:timezone":"America/Guyana",
    "iso:country":"GY",
    "wof:name":"Wai-Wai",
    "wof:placetype":"locality"
},
  "geometry": {"coordinates":[-58.65,1.58333],"type":"Point"}
}