{
  "type": "Feature",
  "properties": {
    "gn:admin1_code":"15",
    "gn:asciiname":"Moca Moca",
    "gn:country_code":"GY",
    "gn:dem":2,
    "gn:feature_class":"P",
    "gn:feature_code":"PPLL",
    "gn:name":"Moca Moca",
    "gn:population":0,
    "gn:timezone":"America/Guyana",
    "iso:country":"GY",
    "name:und_x_variant":[
        "Mocomoco"
    ],
    "wof:name":"Moca Moca",
    "wof:placetype":"locality"
},
  "geometry": {"coordinates":[-57.78682,6.4745],"type":"Point"}
}