{
  "type": "Feature",
  "properties": {
    "gn:admin1_code":"12",
    "gn:asciiname":"Courida Park",
    "gn:country_code":"GY",
    "gn:dem":5,
    "gn:feature_class":"P",
    "gn:feature_code":"PPL",
    "gn:name":"Courida Park",
    "gn:population":0,
    "gn:timezone":"America/Guyana",
    "iso:country":"GY",
    "wof:name":"Courida Park",
    "wof:placetype":"locality"
},
  "geometry": {"coordinates":[-58.10739,6.81642],"type":"Point"}
}