{
  "type": "Feature",
  "properties": {
    "gn:admin1_code":"15",
    "gn:asciiname":"Barabara",
    "gn:country_code":"GY",
    "gn:dem":2,
    "gn:feature_class":"P",
    "gn:feature_code":"PPL",
    "gn:name":"Barabara",
    "gn:population":0,
    "gn:timezone":"America/Guyana",
    "iso:country":"GY",
    "name:deu_x_preferred":[
        "Barabara"
    ],
    "name:hun_x_preferred":[
        "Barabara"
    ],
    "name:rus_x_preferred":[
        "\u0411\u0430\u0440\u0430\u0431\u043e\u0440\u0430"
    ],
    "name:tur_x_preferred":[
        "Aleut evi"
    ],
    "wof:name":"Barabara",
    "wof:placetype":"locality"
},
  "geometry": {"coordinates":[-57.88333000000001,6.55],"type":"Point"}
}