{
  "type": "Feature",
  "properties": {
    "gn:admin1_code":"16",
    "gn:asciiname":"Bounty Hall",
    "gn:country_code":"GY",
    "gn:dem":0,
    "gn:feature_class":"P",
    "gn:feature_code":"PPL",
    "gn:name":"Bounty Hall",
    "gn:population":0,
    "gn:timezone":"America/Guyana",
    "iso:country":"GY",
    "wof:name":"Bounty Hall",
    "wof:placetype":"locality"
},
  "geometry": {"coordinates":[-58.51667,7.36667],"type":"Point"}
}