{
  "type": "Feature",
  "properties": {
    "gn:admin1_code":"18",
    "gn:asciiname":"Riverview",
    "gn:country_code":"GY",
    "gn:dem":6,
    "gn:feature_class":"P",
    "gn:feature_code":"PPLL",
    "gn:name":"Riverview",
    "gn:population":0,
    "gn:timezone":"America/Guyana",
    "iso:country":"GY",
    "name:ceb_x_preferred":[
        "Riverview"
    ],
    "name:deu_x_preferred":[
        "Riverview"
    ],
    "name:fra_x_preferred":[
        "Riverview"
    ],
    "name:ind_x_preferred":[
        "Riverview"
    ],
    "name:ita_x_preferred":[
        "Riverview"
    ],
    "name:mlg_x_preferred":[
        "Riverview"
    ],
    "name:nld_x_preferred":[
        "Riverview"
    ],
    "name:pol_x_preferred":[
        "Riverview"
    ],
    "name:por_x_preferred":[
        "Riverview"
    ],
    "name:ron_x_preferred":[
        "Riverview"
    ],
    "name:rus_x_preferred":[
        "\u0420\u0438\u0432\u0435\u0440\u0432\u044c\u044e"
    ],
    "name:srp_x_preferred":[
        "\u0420\u0438\u0432\u0435\u0440\u0432\u0458\u0443"
    ],
    "name:swe_x_preferred":[
        "Riverview"
    ],
    "name:vol_x_preferred":[
        "Riverview"
    ],
    "wof:name":"Riverview",
    "wof:placetype":"locality"
},
  "geometry": {"coordinates":[-58.59254,6.43843],"type":"Point"}
}