{
  "type": "Feature",
  "properties": {
    "gn:admin1_code":"18",
    "gn:asciiname":"Riverview",
    "gn:country_code":"GY",
    "gn:dem":6,
    "gn:feature_class":"P",
    "gn:feature_code":"PPLL",
    "gn:name":"Riverview",
    "gn:population":0,
    "gn:timezone":"America/Guyana",
    "iso:country":"GY",
    "wof:name":"Riverview",
    "wof:placetype":"locality"
},
  "geometry": {"coordinates":[-58.59254,6.43843],"type":"Point"}
}