{
  "type": "Feature",
  "properties": {
    "gn:admin1_code":"19",
    "gn:asciiname":"Kataliriwau Outstation",
    "gn:country_code":"GY",
    "gn:dem":148,
    "gn:feature_class":"P",
    "gn:feature_code":"PPL",
    "gn:name":"Kataliriwau Outstation",
    "gn:population":0,
    "gn:timezone":"America/Guyana",
    "iso:country":"GY",
    "wof:name":"Kataliriwau Outstation",
    "wof:placetype":"locality"
},
  "geometry": {"coordinates":[-59.25,2.81667],"type":"Point"}
}