{
  "type": "Feature",
  "properties": {
    "gn:admin1_code":"15",
    "gn:asciiname":"Catherine",
    "gn:country_code":"GY",
    "gn:dem":4,
    "gn:feature_class":"P",
    "gn:feature_code":"PPL",
    "gn:name":"Catherine",
    "gn:population":0,
    "gn:timezone":"America/Guyana",
    "iso:country":"GY",
    "name:bre_x_preferred":[
        "Catherine"
    ],
    "name:csb_x_preferred":[
        "Katarz\u00ebn\u00f4"
    ],
    "name:deu_x_preferred":[
        "Catherine"
    ],
    "name:fin_x_preferred":[
        "Catherine"
    ],
    "name:fra_x_preferred":[
        "Catherine"
    ],
    "name:ltz_x_preferred":[
        "Catherine"
    ],
    "name:nor_x_preferred":[
        "Catherine"
    ],
    "wof:name":"Catherine",
    "wof:placetype":"locality"
},
  "geometry": {"coordinates":[-57.74734,6.54861],"type":"Point"}
}