{
  "type": "Feature",
  "properties": {
    "gn:admin1_code":"12",
    "gn:asciiname":"Hyde Park",
    "gn:country_code":"GY",
    "gn:dem":7,
    "gn:feature_class":"P",
    "gn:feature_code":"PPLL",
    "gn:name":"Hyde Park",
    "gn:population":0,
    "gn:timezone":"America/Guyana",
    "iso:country":"GY",
    "wof:name":"Hyde Park",
    "wof:placetype":"locality"
},
  "geometry": {"coordinates":[-58.26864000000001,6.51023],"type":"Point"}
}