{
  "type": "Feature",
  "properties": {
    "gn:admin1_code":"13",
    "gn:asciiname":"Hampshire",
    "gn:country_code":"GY",
    "gn:dem":3,
    "gn:feature_class":"P",
    "gn:feature_code":"PPLL",
    "gn:name":"Hampshire",
    "gn:population":0,
    "gn:timezone":"America/Guyana",
    "iso:country":"GY",
    "wof:name":"Hampshire",
    "wof:placetype":"locality"
},
  "geometry": {"coordinates":[-57.36626999999999,6.25012],"type":"Point"}
}