{
  "type": "Feature",
  "properties": {
    "gn:admin1_code":"11",
    "gn:asciiname":"Kurachi",
    "gn:country_code":"GY",
    "gn:dem":121,
    "gn:feature_class":"P",
    "gn:feature_code":"PPL",
    "gn:name":"Kurachi",
    "gn:population":0,
    "gn:timezone":"America/Guyana",
    "iso:country":"GY",
    "wof:name":"Kurachi",
    "wof:placetype":"locality"
},
  "geometry": {"coordinates":[-60.26667,6.88333],"type":"Point"}
}