{
  "type": "Feature",
  "properties": {
    "gn:admin1_code":"10",
    "gn:asciiname":"Red Hill Settlement",
    "gn:country_code":"GY",
    "gn:dem":19,
    "gn:feature_class":"P",
    "gn:feature_code":"PPL",
    "gn:name":"Red Hill Settlement",
    "gn:population":0,
    "gn:timezone":"America/Guyana",
    "iso:country":"GY",
    "wof:name":"Red Hill Settlement",
    "wof:placetype":"locality"
},
  "geometry": {"coordinates":[-59.43333000000001,7.86667],"type":"Point"}
}