{
  "type": "Feature",
  "properties": {
    "iso:country":"GY",
    "name:eng_x_preferred":[
        "La Penitence"
    ],
    "qs:gn_adm0_cc":"GY",
    "qs:gn_local":3378644,
    "qs:local_max":1085,
    "qs:local_sum":2534,
    "qs:localhoods":7,
    "qs:name":"La Penitence",
    "qs:name_adm0":"Guyana",
    "qs:name_adm1":"Demerara-Mahaica",
    "qs:name_local":"Georgetown",
    "qs:photo_max":108,
    "qs:photo_sum":150,
    "qs:placetype":"Suburb",
    "qs:quad_count":7,
    "qs:woe_adm0":23424836,
    "qs:woe_adm1":2345605,
    "qs:woe_adm2":0,
    "qs:woe_lau":0,
    "qs:woe_local":376765,
    "qs:woe_ver":"7.10.0",
    "wof:lang":[
        "eng"
    ],
    "wof:name":"La Penitence",
    "wof:placetype":"neighbourhood"
},
  "geometry": {"coordinates":[-58.144841,6.79898],"type":"Point"}
}