{
  "type": "Feature",
  "properties": {
    "gn:admin1_code":"11",
    "gn:asciiname":"Wolga",
    "gn:country_code":"GY",
    "gn:dem":15,
    "gn:feature_class":"P",
    "gn:feature_code":"PPL",
    "gn:name":"Wolga",
    "gn:population":0,
    "gn:timezone":"America/Guyana",
    "iso:country":"GY",
    "wof:name":"Wolga",
    "wof:placetype":"locality"
},
  "geometry": {"coordinates":[-58.61637,6.4724],"type":"Point"}
}