{
  "type": "Feature",
  "properties": {
    "gn:admin1_code":"14",
    "gn:asciiname":"Patentia",
    "gn:country_code":"GY",
    "gn:dem":2,
    "gn:feature_class":"P",
    "gn:feature_code":"PPL",
    "gn:name":"Patentia",
    "gn:population":0,
    "gn:timezone":"America/Guyana",
    "iso:country":"GY",
    "wof:name":"Patentia",
    "wof:placetype":"locality"
},
  "geometry": {"coordinates":[-58.20011,6.69847],"type":"Point"}
}