{
  "type": "Feature",
  "properties": {
    "gn:admin1_code":"14",
    "gn:asciiname":"Banakari",
    "gn:country_code":"GY",
    "gn:dem":19,
    "gn:feature_class":"P",
    "gn:feature_code":"PPL",
    "gn:name":"Banakari",
    "gn:population":0,
    "gn:timezone":"America/Guyana",
    "iso:country":"GY",
    "wof:name":"Banakari",
    "wof:placetype":"locality"
},
  "geometry": {"coordinates":[-58.62756,6.61388],"type":"Point"}
}