{
  "type": "Feature",
  "properties": {
    "gn:admin1_code":"11",
    "gn:asciiname":"Akar Village",
    "gn:cc2":"GY",
    "gn:country_code":"GY",
    "gn:dem":486,
    "gn:feature_class":"P",
    "gn:feature_code":"PPL",
    "gn:name":"Akar Village",
    "gn:population":0,
    "gn:timezone":"America/Guyana",
    "iso:country":"GY",
    "name:und_x_variant":[
        "Akar",
        "Akar Village"
    ],
    "wof:name":"Akar Village",
    "wof:placetype":"locality"
},
  "geometry": {"coordinates":[-60.31667,5.68333],"type":"Point"}
}