{
  "type": "Feature",
  "properties": {
    "gn:admin1_code":"14",
    "gn:asciiname":"Bachelors Adventure",
    "gn:country_code":"GY",
    "gn:dem":-1,
    "gn:feature_class":"P",
    "gn:feature_code":"PPL",
    "gn:name":"Bachelors Adventure",
    "gn:population":0,
    "gn:timezone":"America/Guyana",
    "iso:country":"GY",
    "name:und_x_variant":[
        "Batchelor\u2019s Adventure",
        "Waterloo"
    ],
    "wof:name":"Bachelors Adventure",
    "wof:placetype":"locality"
},
  "geometry": {"coordinates":[-58.42164,6.91268],"type":"Point"}
}