{
  "type": "Feature",
  "properties": {
    "gn:admin1_code":"13",
    "gn:asciiname":"Epira",
    "gn:cc2":"GY",
    "gn:country_code":"GY",
    "gn:dem":21,
    "gn:feature_class":"P",
    "gn:feature_code":"PPL",
    "gn:name":"Epira",
    "gn:population":0,
    "gn:timezone":"America/Guyana",
    "iso:country":"GY",
    "name:und_x_variant":[
        "Epira Mission",
        "Espera",
        "Epira"
    ],
    "wof:name":"Epira",
    "wof:placetype":"locality"
},
  "geometry": {"coordinates":[-57.33333,5.13333],"type":"Point"}
}