{
  "type": "Feature",
  "properties": {
    "gn:admin1_code":"13",
    "gn:asciiname":"Number Sixty-two",
    "gn:country_code":"GY",
    "gn:dem":6,
    "gn:feature_class":"P",
    "gn:feature_code":"PPL",
    "gn:name":"Number Sixty-two",
    "gn:population":0,
    "gn:timezone":"America/Guyana",
    "iso:country":"GY",
    "wof:name":"Number Sixty-two",
    "wof:placetype":"locality"
},
  "geometry": {"coordinates":[-57.16158000000001,5.99069],"type":"Point"}
}