{
  "type": "Feature",
  "properties": {
    "gn:admin1_code":"10",
    "gn:asciiname":"Baramita",
    "gn:country_code":"GY",
    "gn:dem":133,
    "gn:feature_class":"P",
    "gn:feature_code":"PPL",
    "gn:name":"Baramita",
    "gn:population":0,
    "gn:timezone":"America/Guyana",
    "iso:country":"GY",
    "name:spa_x_preferred":[
        "Baramita"
    ],
    "wof:name":"Baramita",
    "wof:placetype":"locality"
},
  "geometry": {"coordinates":[-60.48333,7.35],"type":"Point"}
}