{
  "type": "Feature",
  "properties": {
    "gn:admin1_code":"14",
    "gn:asciiname":"Tuschen",
    "gn:country_code":"GY",
    "gn:dem":0,
    "gn:feature_class":"P",
    "gn:feature_code":"PPL",
    "gn:name":"Tuschen",
    "gn:population":0,
    "gn:timezone":"America/Guyana",
    "iso:country":"GY",
    "wof:name":"Tuschen",
    "wof:placetype":"locality"
},
  "geometry": {"coordinates":[-58.35,6.88333],"type":"Point"}
}