{
  "type": "Feature",
  "properties": {
    "gn:admin1_code":"19",
    "gn:asciiname":"Manari",
    "gn:country_code":"GY",
    "gn:dem":82,
    "gn:feature_class":"P",
    "gn:feature_code":"PPL",
    "gn:name":"Manari",
    "gn:population":0,
    "gn:timezone":"America/Guyana",
    "iso:country":"GY",
    "name:ceb_x_preferred":[
        "Manari"
    ],
    "name:new_x_preferred":[
        "\u092e\u0928\u094c\u0930\u0940"
    ],
    "name:swe_x_preferred":[
        "Manari"
    ],
    "wof:name":"Manari",
    "wof:placetype":"locality"
},
  "geometry": {"coordinates":[-59.76667,3.43333],"type":"Point"}
}