{
  "type": "Feature",
  "properties": {
    "gn:admin1_code":"13",
    "gn:asciiname":"Lesbeholden",
    "gn:country_code":"GY",
    "gn:dem":5,
    "gn:feature_class":"P",
    "gn:feature_code":"PPL",
    "gn:name":"Lesbeholden",
    "gn:population":0,
    "gn:timezone":"America/Guyana",
    "iso:country":"GY",
    "wof:name":"Lesbeholden",
    "wof:placetype":"locality"
},
  "geometry": {"coordinates":[-57.30187,6.14633],"type":"Point"}
}