{
  "type": "Feature",
  "properties": {
    "gn:admin1_code":"11",
    "gn:asciiname":"The Clip",
    "gn:cc2":"GY",
    "gn:country_code":"GY",
    "gn:dem":49,
    "gn:feature_class":"P",
    "gn:feature_code":"PPL",
    "gn:name":"The Clip",
    "gn:population":0,
    "gn:timezone":"America/Guyana",
    "iso:country":"GY",
    "name:und_x_variant":[
        "Klip",
        "The Clip"
    ],
    "wof:name":"The Clip",
    "wof:placetype":"locality"
},
  "geometry": {"coordinates":[-58.66667,6.38333],"type":"Point"}
}