{
  "type": "Feature",
  "properties": {
    "gn:admin1_code":"15",
    "gn:asciiname":"Saint Francis Mission",
    "gn:country_code":"GY",
    "gn:dem":22,
    "gn:feature_class":"P",
    "gn:feature_code":"PPL",
    "gn:name":"Saint Francis Mission",
    "gn:population":0,
    "gn:timezone":"America/Guyana",
    "iso:country":"GY",
    "name:und_x_variant":[
        "Moraikobe"
    ],
    "wof:name":"Saint Francis Mission",
    "wof:placetype":"locality"
},
  "geometry": {"coordinates":[-57.95084,6.09855],"type":"Point"}
}