{
  "type": "Feature",
  "properties": {
    "gn:gn_country":"GY",
    "gn:gn_fcode":"PPLX",
    "gn:gn_pop":0,
    "iso:country":"GY",
    "name:eng_x_preferred":[
        "Smythfield"
    ],
    "name:unk_x_variant":[
        "Smythfield"
    ],
    "qs:gn_adm0_cc":"GY",
    "qs:gn_fcode":"PPLX",
    "qs:gn_local":3376762,
    "qs:gn_namadm1":"13",
    "qs:gn_name":"Smythfield",
    "qs:local_max":13,
    "qs:local_sum":13,
    "qs:localhoods":1,
    "qs:name":"Smythfield",
    "qs:name_adm0":"Guyana",
    "qs:name_adm1":"East Berbice-Corentyne",
    "qs:name_local":"New Amsterdam",
    "qs:photo_max":4,
    "qs:photo_sum":13,
    "qs:placetype":"Suburb",
    "qs:quad_count":8,
    "qs:woe_adm0":23424836,
    "qs:woe_adm1":2345606,
    "qs:woe_adm2":0,
    "qs:woe_lau":0,
    "qs:woe_local":376766,
    "qs:woe_ver":"7.10.0",
    "qs_pg:aaroncc":"GY",
    "qs_pg:gn_country":"GY",
    "qs_pg:gn_fcode":"PPLX",
    "qs_pg:gn_pop":0,
    "qs_pg:name":"Smythfield",
    "qs_pg:name_adm0":"Guyana",
    "qs_pg:name_adm1":"East Berbice-Corentyne",
    "qs_pg:photos":13,
    "qs_pg:photos_1k":3,
    "qs_pg:photos_9k":1,
    "qs_pg:photos_9r":1,
    "qs_pg:photos_all":13,
    "qs_pg:photos_sr":1,
    "qs_pg:pop_sr":0,
    "qs_pg:qs_pg_placetype":"neighbourhood",
    "qs_pg:qs_pg_placetype_gp":"Suburb",
    "qs_pg:woe_adm0":23424836,
    "wof:lang":[
        "eng"
    ],
    "wof:name":"Smythfield",
    "wof:placetype":"neighbourhood"
},
  "geometry": {"coordinates":[-57.520823,6.246626],"type":"Point"}
}