{
  "type": "Feature",
  "properties": {
    "gn:admin1_code":"15",
    "gn:asciiname":"Number Ten",
    "gn:country_code":"GY",
    "gn:dem":2,
    "gn:feature_class":"P",
    "gn:feature_code":"PPL",
    "gn:name":"Number Ten",
    "gn:population":0,
    "gn:timezone":"America/Guyana",
    "iso:country":"GY",
    "name:und_x_variant":[
        "Number 10"
    ],
    "wof:name":"Number Ten",
    "wof:placetype":"locality"
},
  "geometry": {"coordinates":[-57.88626,6.56851],"type":"Point"}
}