{
  "type": "Feature",
  "properties": {
    "gn:admin1_code":"17",
    "gn:asciiname":"Wandapa Village",
    "gn:cc2":"GY",
    "gn:country_code":"GY",
    "gn:dem":435,
    "gn:feature_class":"P",
    "gn:feature_code":"PPL",
    "gn:name":"Wandapa Village",
    "gn:population":0,
    "gn:timezone":"America/Guyana",
    "iso:country":"GY",
    "name:und_x_variant":[
        "Waudapa Village",
        "Wandapa",
        "Wandapa Village"
    ],
    "wof:name":"Wandapa Village",
    "wof:placetype":"locality"
},
  "geometry": {"coordinates":[-59.71666999999999,4.55],"type":"Point"}
}