{
  "type": "Feature",
  "properties": {
    "gn:admin1_code":"10",
    "gn:asciiname":"Hobediah",
    "gn:country_code":"GY",
    "gn:dem":10,
    "gn:feature_class":"P",
    "gn:feature_code":"PPL",
    "gn:name":"Hobediah",
    "gn:population":0,
    "gn:timezone":"America/Guyana",
    "iso:country":"GY",
    "wof:name":"Hobediah",
    "wof:placetype":"locality"
},
  "geometry": {"coordinates":[-59.81667,7.96667],"type":"Point"}
}