{
  "type": "Feature",
  "properties": {
    "gn:admin1_code":"12",
    "gn:asciiname":"Golden Grove",
    "gn:country_code":"GY",
    "gn:dem":3,
    "gn:feature_class":"P",
    "gn:feature_code":"PPL",
    "gn:name":"Golden Grove",
    "gn:population":0,
    "gn:timezone":"America/Guyana",
    "iso:country":"GY",
    "name:ceb_x_preferred":[
        "Golden Grove"
    ],
    "name:deu_x_preferred":[
        "Golden Grove"
    ],
    "name:ita_x_preferred":[
        "Golden Grove"
    ],
    "name:mlg_x_preferred":[
        "Golden Grove"
    ],
    "name:nld_x_preferred":[
        "Golden Grove"
    ],
    "name:spa_x_preferred":[
        "Golden Grove"
    ],
    "name:swe_x_preferred":[
        "Golden Grove"
    ],
    "wof:name":"Golden Grove",
    "wof:placetype":"locality"
},
  "geometry": {"coordinates":[-58.18307,6.70348],"type":"Point"}
}