{
  "type": "Feature",
  "properties": {
    "gn:admin1_code":"14",
    "gn:asciiname":"Spring Garden",
    "gn:country_code":"GY",
    "gn:dem":13,
    "gn:feature_class":"P",
    "gn:feature_code":"PPLL",
    "gn:name":"Spring Garden",
    "gn:population":0,
    "gn:timezone":"America/Guyana",
    "iso:country":"GY",
    "name:ceb_x_preferred":[
        "Spring Garden"
    ],
    "name:deu_x_preferred":[
        "Spring Garden"
    ],
    "name:ita_x_preferred":[
        "Spring Garden"
    ],
    "name:pol_x_preferred":[
        "Spring Garden"
    ],
    "name:srp_x_preferred":[
        "\u0421\u043f\u0440\u0438\u043d\u0433 \u0413\u0430\u0440\u0434\u0435\u043d"
    ],
    "name:swe_x_preferred":[
        "Spring Garden"
    ],
    "name:tur_x_preferred":[
        "Spring Garden"
    ],
    "wof:name":"Spring Garden",
    "wof:placetype":"locality"
},
  "geometry": {"coordinates":[-58.26902,6.29734],"type":"Point"}
}