{
  "type": "Feature",
  "properties": {
    "gn:admin1_code":"14",
    "gn:asciiname":"La Grange",
    "gn:country_code":"GY",
    "gn:dem":1,
    "gn:feature_class":"P",
    "gn:feature_code":"PPL",
    "gn:name":"La Grange",
    "gn:population":0,
    "gn:timezone":"America/Guyana",
    "iso:country":"GY",
    "name:deu_x_preferred":[
        "La Grange"
    ],
    "name:nld_x_preferred":[
        "La Grange"
    ],
    "wof:name":"La Grange",
    "wof:placetype":"locality"
},
  "geometry": {"coordinates":[-58.20766,6.77473],"type":"Point"}
}