{
  "type": "Feature",
  "properties": {
    "gn:admin1_code":"16",
    "gn:asciiname":"Marlborough",
    "gn:country_code":"GY",
    "gn:dem":4,
    "gn:feature_class":"P",
    "gn:feature_code":"PPL",
    "gn:name":"Marlborough",
    "gn:population":0,
    "gn:timezone":"America/Guyana",
    "iso:country":"GY",
    "name:bar_x_preferred":[
        "Marlborough"
    ],
    "name:bre_x_preferred":[
        "Marlborough"
    ],
    "name:cat_x_preferred":[
        "Marlborough"
    ],
    "name:ceb_x_preferred":[
        "Marlborough"
    ],
    "name:ces_x_preferred":[
        "Marlborough"
    ],
    "name:dan_x_preferred":[
        "Marlborough"
    ],
    "name:deu_x_preferred":[
        "Marlborough"
    ],
    "name:eng_x_preferred":[
        "Marlborough"
    ],
    "name:epo_x_preferred":[
        "Marlborough"
    ],
    "name:fas_x_preferred":[
        "\u0645\u0627\u0631\u0644\u0628\u0631\u0648"
    ],
    "name:fin_x_preferred":[
        "Marlborough"
    ],
    "name:fra_x_preferred":[
        "Marlborough"
    ],
    "name:heb_x_preferred":[
        "\u05de\u05e8\u05dc\u05d1\u05d5\u05e8\u05d5"
    ],
    "name:ind_x_preferred":[
        "Marlborough"
    ],
    "name:ita_x_preferred":[
        "Marlborough"
    ],
    "name:jpn_x_preferred":[
        "\u30de\u30fc\u30eb\u30d0\u30e9"
    ],
    "name:kor_x_preferred":[
        "\ub9d0\ubc84\ub7ec"
    ],
    "name:nld_x_preferred":[
        "Marlborough"
    ],
    "name:nor_x_preferred":[
        "Marlborough"
    ],
    "name:pol_x_preferred":[
        "Marlborough"
    ],
    "name:por_x_preferred":[
        "Marlborough"
    ],
    "name:spa_x_preferred":[
        "Marlborough"
    ],
    "name:srp_x_preferred":[
        "\u041c\u0430\u0440\u043b\u0431\u043e\u0440\u043e"
    ],
    "name:swe_x_preferred":[
        "Marlborough"
    ],
    "name:tha_x_preferred":[
        "\u0e21\u0e32\u0e23\u0e4c\u0e25\u0e1a\u0e30\u0e23\u0e30"
    ],
    "name:ukr_x_preferred":[
        "\u041c\u0430\u0440\u043b\u0431\u043e\u0440\u043e"
    ],
    "name:vol_x_preferred":[
        "Marlborough"
    ],
    "wof:name":"Marlborough",
    "wof:placetype":"locality"
},
  "geometry": {"coordinates":[-58.64378000000001,7.49379],"type":"Point"}
}