{
  "type": "Feature",
  "properties": {
    "gn:admin1_code":"16",
    "gn:asciiname":"Marlborough",
    "gn:country_code":"GY",
    "gn:dem":4,
    "gn:feature_class":"P",
    "gn:feature_code":"PPL",
    "gn:name":"Marlborough",
    "gn:population":0,
    "gn:timezone":"America/Guyana",
    "iso:country":"GY",
    "name:eng_x_preferred":[
        "Marlborough"
    ],
    "wof:name":"Marlborough",
    "wof:placetype":"locality"
},
  "geometry": {"coordinates":[-58.64378000000001,7.49379],"type":"Point"}
}