{
  "type": "Feature",
  "properties": {
    "gn:admin1_code":"16",
    "gn:asciiname":"Tuschen",
    "gn:country_code":"GY",
    "gn:dem":7,
    "gn:feature_class":"P",
    "gn:feature_code":"PPL",
    "gn:name":"Tuschen",
    "gn:population":0,
    "gn:timezone":"America/Guyana",
    "iso:country":"GY",
    "name:eng_x_preferred":[
        "Tuschen"
    ],
    "wof:name":"Tuschen",
    "wof:placetype":"locality"
},
  "geometry": {"coordinates":[-58.73958,7.59993],"type":"Point"}
}