{
  "type": "Feature",
  "properties": {
    "gn:admin1_code":"12",
    "gn:asciiname":"Cane Grove",
    "gn:country_code":"GY",
    "gn:dem":1,
    "gn:feature_class":"P",
    "gn:feature_code":"PPL",
    "gn:name":"Cane Grove",
    "gn:population":0,
    "gn:timezone":"America/Guyana",
    "iso:country":"GY",
    "name:ceb_x_preferred":[
        "Cane Grove"
    ],
    "name:spa_x_preferred":[
        "Cane Grove"
    ],
    "name:swe_x_preferred":[
        "Cane Grove"
    ],
    "wof:name":"Cane Grove",
    "wof:placetype":"locality"
},
  "geometry": {"coordinates":[-57.91767,6.62797],"type":"Point"}
}