{
  "type": "Feature",
  "properties": {
    "gn:admin1_code":"13",
    "gn:asciiname":"Barakara",
    "gn:cc2":"GY",
    "gn:country_code":"GY",
    "gn:dem":10,
    "gn:feature_class":"P",
    "gn:feature_code":"PPL",
    "gn:name":"Barakara",
    "gn:population":0,
    "gn:timezone":"America/Guyana",
    "iso:country":"GY",
    "name:und_x_variant":[
        "Barakara Mission",
        "Barakara"
    ],
    "wof:name":"Barakara",
    "wof:placetype":"locality"
},
  "geometry": {"coordinates":[-57.46666999999999,5.85],"type":"Point"}
}