{
  "type": "Feature",
  "properties": {
    "gn:admin1_code":"11",
    "gn:asciiname":"Morowta",
    "gn:country_code":"GY",
    "gn:dem":525,
    "gn:feature_class":"P",
    "gn:feature_code":"PPL",
    "gn:name":"Morowta",
    "gn:population":0,
    "gn:timezone":"America/Guyana",
    "iso:country":"GY",
    "wof:name":"Morowta",
    "wof:placetype":"locality"
},
  "geometry": {"coordinates":[-60.58333,5.75],"type":"Point"}
}