{
  "type": "Feature",
  "properties": {
    "gn:admin1_code":"16",
    "gn:asciiname":"Amazon",
    "gn:country_code":"GY",
    "gn:dem":2,
    "gn:feature_class":"P",
    "gn:feature_code":"PPL",
    "gn:name":"Amazon",
    "gn:population":0,
    "gn:timezone":"America/Guyana",
    "iso:country":"GY",
    "wof:name":"Amazon",
    "wof:placetype":"locality"
},
  "geometry": {"coordinates":[-58.58333,7.38333],"type":"Point"}
}