{
  "type": "Feature",
  "properties": {
    "gn:admin1_code":"16",
    "gn:asciiname":"Amazon",
    "gn:country_code":"GY",
    "gn:dem":2,
    "gn:feature_class":"P",
    "gn:feature_code":"PPL",
    "gn:name":"Amazon",
    "gn:population":0,
    "gn:timezone":"America/Guyana",
    "iso:country":"GY",
    "name:ara_x_preferred":[
        "\u0623\u0645\u0627\u0632\u0648\u0646"
    ],
    "name:asm_x_preferred":[
        "\u0986\u09ae\u09be\u099c\u09a8"
    ],
    "name:bih_x_preferred":[
        "\u0905\u092e\u0947\u091c\u0928"
    ],
    "name:cat_x_preferred":[
        "Amazon"
    ],
    "name:cym_x_preferred":[
        "Amazon"
    ],
    "name:deu_x_preferred":[
        "Amazon"
    ],
    "name:fas_x_preferred":[
        "\u0622\u0645\u0627\u0632\u0648\u0646"
    ],
    "name:fin_x_preferred":[
        "Amazon"
    ],
    "name:fra_x_preferred":[
        "Amazon"
    ],
    "name:hun_x_preferred":[
        "Amazon"
    ],
    "name:ind_x_preferred":[
        "Amazon"
    ],
    "name:isl_x_preferred":[
        "Amazon"
    ],
    "name:ita_x_preferred":[
        "Amazon"
    ],
    "name:jav_x_preferred":[
        "Amazon"
    ],
    "name:jpn_x_preferred":[
        "\u30a2\u30de\u30be\u30f3"
    ],
    "name:kat_x_preferred":[
        "\u10d0\u10db\u10d0\u10d6\u10dd\u10dc\u10d8"
    ],
    "name:kor_x_preferred":[
        "\uc544\ub9c8\uc874"
    ],
    "name:mal_x_preferred":[
        "\u0d06\u0d2e\u0d38\u0d4b\u0d7a"
    ],
    "name:mkd_x_preferred":[
        "\u0410\u043c\u0430\u0437\u043e\u043d"
    ],
    "name:nld_x_preferred":[
        "Amazon"
    ],
    "name:ron_x_preferred":[
        "Amazon"
    ],
    "name:sco_x_preferred":[
        "Amazon"
    ],
    "name:slk_x_preferred":[
        "Amazon"
    ],
    "name:slv_x_preferred":[
        "Amazon"
    ],
    "name:spa_x_preferred":[
        "Amazon"
    ],
    "name:sqi_x_preferred":[
        "Amazon"
    ],
    "name:srp_x_preferred":[
        "\u0410\u043c\u0430\u0437\u043e\u043d"
    ],
    "name:swe_x_preferred":[
        "Amazon"
    ],
    "name:tam_x_preferred":[
        "\u0b85\u0bae\u0bc7\u0b9a\u0bbe\u0ba9\u0bcd"
    ],
    "name:tha_x_preferred":[
        "\u0e41\u0e2d\u0e21\u0e30\u0e0b\u0e2d\u0e19"
    ],
    "name:tur_x_preferred":[
        "Amazon"
    ],
    "name:urd_x_preferred":[
        "\u0627\u06cc\u0645\u0632\u0648\u0646"
    ],
    "name:vie_x_preferred":[
        "Amazon"
    ],
    "name:zho_x_preferred":[
        "\u4e9a\u9a6c\u5b59"
    ],
    "wof:name":"Amazon",
    "wof:placetype":"locality"
},
  "geometry": {"coordinates":[-58.58333,7.38333],"type":"Point"}
}