{
  "type": "Feature",
  "properties": {
    "gn:admin1_code":"13",
    "gn:asciiname":"Resource",
    "gn:country_code":"GY",
    "gn:dem":8,
    "gn:feature_class":"P",
    "gn:feature_code":"PPLL",
    "gn:name":"Resource",
    "gn:population":0,
    "gn:timezone":"America/Guyana",
    "iso:country":"GY",
    "name:ara_x_preferred":[
        "\u0645\u0648\u0631\u062f"
    ],
    "name:aze_x_preferred":[
        "Resurslar"
    ],
    "name:bih_x_preferred":[
        "\u0938\u0902\u0938\u093e\u0927\u0928"
    ],
    "name:dan_x_preferred":[
        "Resurse"
    ],
    "name:deu_x_preferred":[
        "Ressource"
    ],
    "name:epo_x_preferred":[
        "Resurso"
    ],
    "name:est_x_preferred":[
        "Ressursid"
    ],
    "name:fin_x_preferred":[
        "Resurssi"
    ],
    "name:heb_x_preferred":[
        "\u05de\u05e9\u05d0\u05d1"
    ],
    "name:hin_x_preferred":[
        "\u0938\u0902\u0938\u093e\u0927\u0928"
    ],
    "name:hrv_x_preferred":[
        "Resurs"
    ],
    "name:ind_x_preferred":[
        "Sumber daya"
    ],
    "name:jav_x_preferred":[
        "Sumber daya"
    ],
    "name:lav_x_preferred":[
        "Resurss"
    ],
    "name:lit_x_preferred":[
        "I\u0161teklius"
    ],
    "name:nld_x_preferred":[
        "Bestaansmiddelen"
    ],
    "name:nor_x_preferred":[
        "Ressurs"
    ],
    "name:pan_x_preferred":[
        "\u0a35\u0a38\u0a40\u0a32\u0a3e"
    ],
    "name:pol_x_preferred":[
        "Zasoby"
    ],
    "name:spa_x_preferred":[
        "Recurso"
    ],
    "name:sqi_x_preferred":[
        "Burimi"
    ],
    "name:srp_x_preferred":[
        "\u0420\u0435\u0441\u0443\u0440\u0441\u0438"
    ],
    "name:swe_x_preferred":[
        "Resurs"
    ],
    "name:tam_x_preferred":[
        "\u0bae\u0bc2\u0bb2\u0bb5\u0bb3\u0b99\u0bcd\u0b95\u0bb3\u0bcd"
    ],
    "name:tha_x_preferred":[
        "\u0e17\u0e23\u0e31\u0e1e\u0e22\u0e32\u0e01\u0e23"
    ],
    "name:ukr_x_preferred":[
        "\u0420\u0435\u0441\u0443\u0440\u0441\u0438"
    ],
    "wof:name":"Resource",
    "wof:placetype":"locality"
},
  "geometry": {"coordinates":[-57.34091,6.23998],"type":"Point"}
}