{
  "type": "Feature",
  "properties": {
    "gn:admin1_code":"13",
    "gn:asciiname":"Resource",
    "gn:country_code":"GY",
    "gn:dem":8,
    "gn:feature_class":"P",
    "gn:feature_code":"PPLL",
    "gn:name":"Resource",
    "gn:population":0,
    "gn:timezone":"America/Guyana",
    "iso:country":"GY",
    "wof:name":"Resource",
    "wof:placetype":"locality"
},
  "geometry": {"coordinates":[-57.34091,6.23998],"type":"Point"}
}