{
  "type": "Feature",
  "properties": {
    "gn:admin1_code":"10",
    "gn:asciiname":"La Juanita",
    "gn:cc2":"GY",
    "gn:country_code":"GY",
    "gn:dem":69,
    "gn:feature_class":"P",
    "gn:feature_code":"PPL",
    "gn:name":"La Juanita",
    "gn:population":0,
    "gn:timezone":"America/Guyana",
    "iso:country":"GY",
    "name:und_x_variant":[
        "Juanita",
        "La Juanita"
    ],
    "wof:name":"La Juanita",
    "wof:placetype":"locality"
},
  "geometry": {"coordinates":[-60.21666999999999,7.95],"type":"Point"}
}