{
  "type": "Feature",
  "properties": {
    "gn:admin1_code":"15",
    "gn:asciiname":"Lichfield",
    "gn:country_code":"GY",
    "gn:dem":3,
    "gn:feature_class":"P",
    "gn:feature_code":"PPL",
    "gn:name":"Lichfield",
    "gn:population":0,
    "gn:timezone":"America/Guyana",
    "iso:country":"GY",
    "wof:name":"Lichfield",
    "wof:placetype":"locality"
},
  "geometry": {"coordinates":[-57.66147,6.46761],"type":"Point"}
}