{
  "type": "Feature",
  "properties": {
    "gn:admin1_code":"15",
    "gn:asciiname":"Lichfield",
    "gn:country_code":"GY",
    "gn:dem":3,
    "gn:feature_class":"P",
    "gn:feature_code":"PPL",
    "gn:name":"Lichfield",
    "gn:population":0,
    "gn:timezone":"America/Guyana",
    "iso:country":"GY",
    "name:ang_x_preferred":[
        "Liccidfeld"
    ],
    "name:ast_x_preferred":[
        "Lichfield"
    ],
    "name:azb_x_preferred":[
        "\u0644\u06cc\u0686\u0641\u06cc\u0644\u062f"
    ],
    "name:bre_x_preferred":[
        "Lichfield"
    ],
    "name:bul_x_preferred":[
        "\u041b\u0438\u0447\u0444\u0438\u0439\u043b\u0434"
    ],
    "name:cat_x_preferred":[
        "Lichfield"
    ],
    "name:ceb_x_preferred":[
        "Lichfield"
    ],
    "name:ces_x_preferred":[
        "Lichfield"
    ],
    "name:cym_x_preferred":[
        "Lichfield"
    ],
    "name:dan_x_preferred":[
        "Lichfield"
    ],
    "name:deu_x_preferred":[
        "Lichfield"
    ],
    "name:epo_x_preferred":[
        "Lichfield"
    ],
    "name:eus_x_preferred":[
        "Lichfield"
    ],
    "name:fas_x_preferred":[
        "\u0644\u06cc\u0686\u0641\u06cc\u0644\u062f"
    ],
    "name:fin_x_preferred":[
        "Lichfield"
    ],
    "name:fra_x_preferred":[
        "Lichfield"
    ],
    "name:fry_x_preferred":[
        "Lichfield"
    ],
    "name:gle_x_preferred":[
        "Lichfield"
    ],
    "name:glg_x_preferred":[
        "Lichfield"
    ],
    "name:hye_x_preferred":[
        "\u053c\u056b\u0579\u0586\u056b\u056c\u0564"
    ],
    "name:ind_x_preferred":[
        "Lichfield"
    ],
    "name:isl_x_preferred":[
        "Lichfield"
    ],
    "name:ita_x_preferred":[
        "Lichfield"
    ],
    "name:jpn_x_preferred":[
        "\u30ea\u30c3\u30c1\u30d5\u30a3\u30fc\u30eb\u30c9"
    ],
    "name:kor_x_preferred":[
        "\ub9ac\uce58\ud544\ub4dc"
    ],
    "name:mzn_x_preferred":[
        "\u0644\u06cc\u0686\u0641\u06cc\u0644\u062f"
    ],
    "name:nld_x_preferred":[
        "Lichfield"
    ],
    "name:nno_x_preferred":[
        "Lichfield"
    ],
    "name:nor_x_preferred":[
        "Lichfield"
    ],
    "name:pnb_x_preferred":[
        "\u0644\u062e\u0641\u06cc\u0644\u0688"
    ],
    "name:pol_x_preferred":[
        "Lichfield"
    ],
    "name:por_x_preferred":[
        "Lichfield"
    ],
    "name:ron_x_preferred":[
        "Lichfield"
    ],
    "name:rus_x_preferred":[
        "\u041b\u0438\u0447\u0444\u0438\u043b\u0434"
    ],
    "name:sco_x_preferred":[
        "Lichfield"
    ],
    "name:spa_x_preferred":[
        "Lichfield"
    ],
    "name:swe_x_preferred":[
        "Lichfield"
    ],
    "name:tgl_x_preferred":[
        "Lichfield"
    ],
    "name:tur_x_preferred":[
        "Lichfield"
    ],
    "name:urd_x_preferred":[
        "\u0644\u06cc\u0686\u0641\u06cc\u0644\u0688"
    ],
    "name:vol_x_preferred":[
        "Lichfield"
    ],
    "name:war_x_preferred":[
        "Lichfield"
    ],
    "name:zho_x_preferred":[
        "\u5229\u5947\u83f2\u723e\u5fb7"
    ],
    "wof:name":"Lichfield",
    "wof:placetype":"locality"
},
  "geometry": {"coordinates":[-57.66147,6.46761],"type":"Point"}
}