{
  "type": "Feature",
  "properties": {
    "gn:admin1_code":"19",
    "gn:asciiname":"Yepu Village",
    "gn:country_code":"GY",
    "gn:dem":292,
    "gn:feature_class":"P",
    "gn:feature_code":"PPL",
    "gn:name":"Yepu Village",
    "gn:population":0,
    "gn:timezone":"America/Guyana",
    "iso:country":"GY",
    "wof:name":"Yepu Village",
    "wof:placetype":"locality"
},
  "geometry": {"coordinates":[-58.63333000000001,1.36667],"type":"Point"}
}