{
  "type": "Feature",
  "properties": {
    "gn:admin1_code":"19",
    "gn:asciiname":"Karasabai Village",
    "gn:cc2":"GY",
    "gn:country_code":"GY",
    "gn:dem":99,
    "gn:feature_class":"P",
    "gn:feature_code":"PPL",
    "gn:name":"Karasabai Village",
    "gn:population":0,
    "gn:timezone":"America/Guyana",
    "iso:country":"GY",
    "name:und_x_variant":[
        "Karasabai",
        "Karasabai Village"
    ],
    "wof:name":"Karasabai Village",
    "wof:placetype":"locality"
},
  "geometry": {"coordinates":[-59.53333000000001,4.03333],"type":"Point"}
}