{
  "type": "Feature",
  "properties": {
    "gn:admin1_code":"13",
    "gn:asciiname":"Number Seventy-one Little Massiah",
    "gn:country_code":"GY",
    "gn:dem":4,
    "gn:feature_class":"P",
    "gn:feature_code":"PPL",
    "gn:name":"Number Seventy-one Little Massiah",
    "gn:population":0,
    "gn:timezone":"America/Guyana",
    "iso:country":"GY",
    "name:und_x_variant":[
        "Number 71",
        "Little Massiah",
        "Number Seventy-one Little Massiah"
    ],
    "wof:name":"Number Seventy-one Little Massiah",
    "wof:placetype":"locality"
},
  "geometry": {"coordinates":[-57.15821,5.93559],"type":"Point"}
}