{
  "type": "Feature",
  "properties": {
    "gn:admin1_code":"14",
    "gn:asciiname":"Stanleytown",
    "gn:country_code":"GY",
    "gn:dem":0,
    "gn:feature_class":"P",
    "gn:feature_code":"PPL",
    "gn:name":"Stanleytown",
    "gn:population":0,
    "gn:timezone":"America/Guyana",
    "iso:country":"GY",
    "wof:name":"Stanleytown",
    "wof:placetype":"locality"
},
  "geometry": {"coordinates":[-58.20508,6.73299],"type":"Point"}
}